{"bar_chart_data": {"1": {"accommodation_type_3a": "blocked", "country_of_birth_3a": "all_zero", "disability_3a": "all_zero", "economic_activity_status_4a": "blocked", "english_proficiency": "blocked", "has_ever_worked": "blocked", "health_in_general": "blocked", "heating_type_3a": "all_zero", "hh_dependent_children_3a": "all_zero", "hh_deprivation": "blocked", "hh_disabled_4a": "blocked", "hh_families_type_6a": "blocked", "hh_family_composition_6a": "blocked", "hh_multi_language_3a": "all_zero", "hh_size_5a": "blocked", "hh_tenure_5a": "blocked", "highest_qualification": "blocked", "hours_per_week_worked": "blocked", "is_carer_5a": "blocked", "legal_partnership_status_6a": "blocked", "national_identity_all_4a": "blocked", "ns_sec_10a": "blocked", "number_bedrooms_5a": "blocked", "number_of_cars_5a": "blocked", "occupancy_rating_bedrooms_6a": "blocked", "occupation_current_10a": "blocked", "passports_all_4a": "blocked", "religion_tb": "blocked", "resident_age_18b": "all_zero", "resident_age_23a": "all_zero", "sex": "all_zero", "transport_to_workplace_12a": "blocked", "workplace_travel_8a": "blocked", "total_pop": {"count": 0, "percent": 0.0}}, "2": {"accommodation_type_3a": "blocked", "country_of_birth_3a": "all_zero", "disability_3a": "all_zero", "economic_activity_status_4a": "blocked", "english_proficiency": "blocked", "has_ever_worked": "blocked", "health_in_general": "blocked", "heating_type_3a": "all_zero", "hh_dependent_children_3a": "all_zero", "hh_deprivation": "blocked", "hh_disabled_4a": "blocked", "hh_families_type_6a": "blocked", "hh_family_composition_6a": "blocked", "hh_multi_language_3a": "all_zero", "hh_size_5a": "blocked", "hh_tenure_5a": "blocked", "highest_qualification": "blocked", "hours_per_week_worked": "blocked", "is_carer_5a": "blocked", "legal_partnership_status_6a": "blocked", "national_identity_all_4a": "blocked", "ns_sec_10a": "blocked", "number_bedrooms_5a": "blocked", "number_of_cars_5a": "blocked", "occupancy_rating_bedrooms_6a": "blocked", "occupation_current_10a": "blocked", "passports_all_4a": "blocked", "religion_tb": "blocked", "resident_age_18b": "all_zero", "resident_age_23a": "all_zero", "sex": "all_zero", "transport_to_workplace_12a": "blocked", "workplace_travel_8a": "blocked", "total_pop": {"count": 0, "percent": 0.0}}, "3": {"accommodation_type_3a": "blocked", "country_of_birth_3a": {"count": [0, 637], "percent": [0.0, 100.0]}, "disability_3a": {"count": [17, 617], "percent": [2.7, 97.3]}, "economic_activity_status_4a": "blocked", "english_proficiency": "blocked", "has_ever_worked": "blocked", "health_in_general": "blocked", "heating_type_3a": {"count": [20, 600], "percent": [3.2, 96.8]}, "hh_dependent_children_3a": {"count": [0, 620], "percent": [0.0, 100.0]}, "hh_deprivation": "blocked", "hh_disabled_4a": "blocked", "hh_families_type_6a": "blocked", "hh_family_composition_6a": "blocked", "hh_multi_language_3a": {"count": [412, 208], "percent": [66.5, 33.5]}, "hh_size_5a": "blocked", "hh_tenure_5a": "blocked", "highest_qualification": "blocked", "hours_per_week_worked": "blocked", "is_carer_5a": "blocked", "legal_partnership_status_6a": "blocked", "national_identity_all_4a": "blocked", "ns_sec_10a": "blocked", "number_bedrooms_5a": "blocked", "number_of_cars_5a": "blocked", "occupancy_rating_bedrooms_6a": "blocked", "occupation_current_10a": "blocked", "passports_all_4a": "blocked", "religion_tb": "blocked", "resident_age_18b": {"count": [0, 0, 637, 0, 0, 0, 0, 0, 0, 0, 0, 0, 0, 0, 0, 0, 0, 0], "percent": [0.0, 0.0, 100.0, 0.0, 0.0, 0.0, 0.0, 0.0, 0.0, 0.0, 0.0, 0.0, 0.0, 0.0, 0.0, 0.0, 0.0, 0.0]}, "resident_age_23a": {"count": [0, 0, 637, 0, 0, 0, 0, 0, 0, 0, 0, 0, 0, 0, 0, 0, 0, 0], "percent": [0.0, 0.0, 100.0, 0.0, 0.0, 0.0, 0.0, 0.0, 0.0, 0.0, 0.0, 0.0, 0.0, 0.0, 0.0, 0.0, 0.0, 0.0]}, "sex": {"count": [337, 297], "percent": [53.2, 46.8]}, "transport_to_workplace_12a": "blocked", "workplace_travel_8a": "blocked", "total_pop": {"count": 637, "percent": 0.0}}, "4": {"accommodation_type_3a": "blocked", "country_of_birth_3a": {"count": [0, 1817], "percent": [0.0, 100.0]}, "disability_3a": {"count": [78, 1739], "percent": [4.3, 95.7]}, "economic_activity_status_4a": "blocked", "english_proficiency": "blocked", "has_ever_worked": "blocked", "health_in_general": "blocked", "heating_type_3a": {"count": [47, 1644], "percent": [2.8, 97.2]}, "hh_dependent_children_3a": {"count": [152, 1539], "percent": [9.0, 91.0]}, "hh_deprivation": "blocked", "hh_disabled_4a": "blocked", "hh_families_type_6a": "blocked", "hh_family_composition_6a": "blocked", "hh_multi_language_3a": {"count": [1089, 602], "percent": [64.4, 35.6]}, "hh_size_5a": "blocked", "hh_tenure_5a": "blocked", "highest_qualification": "blocked", "hours_per_week_worked": "blocked", "is_carer_5a": "blocked", "legal_partnership_status_6a": "blocked", "national_identity_all_4a": "blocked", "ns_sec_10a": "blocked", "number_bedrooms_5a": "blocked", "number_of_cars_5a": "blocked", "occupancy_rating_bedrooms_6a": "blocked", "occupation_current_10a": "blocked", "passports_all_4a": "blocked", "religion_tb": "blocked", "resident_age_18b": {"count": [0, 0, 0, 1817, 0, 0, 0, 0, 0, 0, 0, 0, 0, 0, 0, 0, 0, 0], "percent": [0.0, 0.0, 0.0, 100.0, 0.0, 0.0, 0.0, 0.0, 0.0, 0.0, 0.0, 0.0, 0.0, 0.0, 0.0, 0.0, 0.0, 0.0]}, "resident_age_23a": {"count": [0, 0, 0, 1815, 0, 0, 0, 0, 0, 0, 0, 0, 0, 0, 0, 0, 0, 0], "percent": [0.0, 0.0, 0.0, 100.0, 0.0, 0.0, 0.0, 0.0, 0.0, 0.0, 0.0, 0.0, 0.0, 0.0, 0.0, 0.0, 0.0, 0.0]}, "sex": {"count": [819, 998], "percent": [45.1, 54.9]}, "transport_to_workplace_12a": "blocked", "workplace_travel_8a": "blocked", "total_pop": {"count": 1817, "percent": 0.0}}, "5": {"accommodation_type_3a": "blocked", "country_of_birth_3a": {"count": [0, 2766], "percent": [0.0, 100.0]}, "disability_3a": {"count": [206, 2560], "percent": [7.4, 92.6]}, "economic_activity_status_4a": "blocked", "english_proficiency": "blocked", "has_ever_worked": "blocked", "health_in_general": "blocked", "heating_type_3a": {"count": [53, 2515], "percent": [2.1, 97.9]}, "hh_dependent_children_3a": {"count": [1205, 1363], "percent": [46.9, 53.1]}, "hh_deprivation": "blocked", "hh_disabled_4a": "blocked", "hh_families_type_6a": "blocked", "hh_family_composition_6a": "blocked", "hh_multi_language_3a": {"count": [1668, 903], "percent": [64.9, 35.1]}, "hh_size_5a": "blocked", "hh_tenure_5a": "blocked", "highest_qualification": "blocked", "hours_per_week_worked": "blocked", "is_carer_5a": "blocked", "legal_partnership_status_6a": "blocked", "national_identity_all_4a": "blocked", "ns_sec_10a": "blocked", "number_bedrooms_5a": "blocked", "number_of_cars_5a": "blocked", "occupancy_rating_bedrooms_6a": "blocked", "occupation_current_10a": "blocked", "passports_all_4a": "blocked", "religion_tb": "blocked", "resident_age_18b": {"count": [0, 0, 0, 0, 2766, 0, 0, 0, 0, 0, 0, 0, 0, 0, 0, 0, 0, 0], "percent": [0.0, 0.0, 0.0, 0.0, 100.0, 0.0, 0.0, 0.0, 0.0, 0.0, 0.0, 0.0, 0.0, 0.0, 0.0, 0.0, 0.0, 0.0]}, "resident_age_23a": {"count": [0, 0, 0, 0, 2766, 0, 0, 0, 0, 0, 0, 0, 0, 0, 0, 0, 0, 0], "percent": [0.0, 0.0, 0.0, 0.0, 100.0, 0.0, 0.0, 0.0, 0.0, 0.0, 0.0, 0.0, 0.0, 0.0, 0.0, 0.0, 0.0, 0.0]}, "sex": {"count": [1241, 1525], "percent": [44.9, 55.1]}, "transport_to_workplace_12a": "blocked", "workplace_travel_8a": "blocked", "total_pop": {"count": 2766, "percent": 0.0}}, "6": {"accommodation_type_3a": "blocked", "country_of_birth_3a": {"count": [0, 2517], "percent": [0.0, 100.0]}, "disability_3a": {"count": [238, 2279], "percent": [9.5, 90.5]}, "economic_activity_status_4a": "blocked", "english_proficiency": "blocked", "has_ever_worked": "blocked", "health_in_general": "blocked", "heating_type_3a": {"count": [75, 2363], "percent": [3.1, 96.9]}, "hh_dependent_children_3a": {"count": [1406, 1031], "percent": [57.7, 42.3]}, "hh_deprivation": "blocked", "hh_disabled_4a": "blocked", "hh_families_type_6a": "blocked", "hh_family_composition_6a": "blocked", "hh_multi_language_3a": {"count": [1804, 633], "percent": [74.0, 26.0]}, "hh_size_5a": "blocked", "hh_tenure_5a": "blocked", "highest_qualification": "blocked", "hours_per_week_worked": "blocked", "is_carer_5a": "blocked", "legal_partnership_status_6a": "blocked", "national_identity_all_4a": "blocked", "ns_sec_10a": "blocked", "number_bedrooms_5a": "blocked", "number_of_cars_5a": "blocked", "occupancy_rating_bedrooms_6a": "blocked", "occupation_current_10a": "blocked", "passports_all_4a": "blocked", "religion_tb": "blocked", "resident_age_18b": {"count": [0, 0, 0, 0, 0, 2517, 0, 0, 0, 0, 0, 0, 0, 0, 0, 0, 0, 0], "percent": [0.0, 0.0, 0.0, 0.0, 0.0, 100.0, 0.0, 0.0, 0.0, 0.0, 0.0, 0.0, 0.0, 0.0, 0.0, 0.0, 0.0, 0.0]}, "resident_age_23a": {"count": [0, 0, 0, 0, 0, 2517, 0, 0, 0, 0, 0, 0, 0, 0, 0, 0, 0, 0], "percent": [0.0, 0.0, 0.0, 0.0, 0.0, 100.0, 0.0, 0.0, 0.0, 0.0, 0.0, 0.0, 0.0, 0.0, 0.0, 0.0, 0.0, 0.0]}, "sex": {"count": [1332, 1184], "percent": [52.9, 47.1]}, "transport_to_workplace_12a": "blocked", "workplace_travel_8a": "blocked", "total_pop": {"count": 2517, "percent": 0.0}}, "7": {"accommodation_type_3a": "blocked", "country_of_birth_3a": {"count": [0, 2845], "percent": [0.0, 100.0]}, "disability_3a": {"count": [254, 2591], "percent": [8.9, 91.1]}, "economic_activity_status_4a": "blocked", "english_proficiency": "blocked", "has_ever_worked": "blocked", "health_in_general": "blocked", "heating_type_3a": {"count": [94, 2688], "percent": [3.4, 96.6]}, "hh_dependent_children_3a": {"count": [1212, 1571], "percent": [43.6, 56.4]}, "hh_deprivation": "blocked", "hh_disabled_4a": "blocked", "hh_families_type_6a": "blocked", "hh_family_composition_6a": "blocked", "hh_multi_language_3a": {"count": [2111, 672], "percent": [75.9, 24.1]}, "hh_size_5a": "blocked", "hh_tenure_5a": "blocked", "highest_qualification": "blocked", "hours_per_week_worked": "blocked", "is_carer_5a": "blocked", "legal_partnership_status_6a": "blocked", "national_identity_all_4a": "blocked", "ns_sec_10a": "blocked", "number_bedrooms_5a": "blocked", "number_of_cars_5a": "blocked", "occupancy_rating_bedrooms_6a": "blocked", "occupation_current_10a": "blocked", "passports_all_4a": "blocked", "religion_tb": "blocked", "resident_age_18b": {"count": [0, 0, 0, 0, 0, 0, 2845, 0, 0, 0, 0, 0, 0, 0, 0, 0, 0, 0], "percent": [0.0, 0.0, 0.0, 0.0, 0.0, 0.0, 100.0, 0.0, 0.0, 0.0, 0.0, 0.0, 0.0, 0.0, 0.0, 0.0, 0.0, 0.0]}, "resident_age_23a": {"count": [0, 0, 0, 0, 0, 0, 2845, 0, 0, 0, 0, 0, 0, 0, 0, 0, 0, 0], "percent": [0.0, 0.0, 0.0, 0.0, 0.0, 0.0, 100.0, 0.0, 0.0, 0.0, 0.0, 0.0, 0.0, 0.0, 0.0, 0.0, 0.0, 0.0]}, "sex": {"count": [1604, 1241], "percent": [56.4, 43.6]}, "transport_to_workplace_12a": "blocked", "workplace_travel_8a": "blocked", "total_pop": {"count": 2845, "percent": 0.0}}, "8": {"accommodation_type_3a": "blocked", "country_of_birth_3a": {"count": [0, 3714], "percent": [0.0, 100.0]}, "disability_3a": {"count": [374, 3340], "percent": [10.1, 89.9]}, "economic_activity_status_4a": "blocked", "english_proficiency": "blocked", "has_ever_worked": "blocked", "health_in_general": "blocked", "heating_type_3a": {"count": [112, 3519], "percent": [3.1, 96.9]}, "hh_dependent_children_3a": {"count": [1132, 2499], "percent": [31.2, 68.8]}, "hh_deprivation": "blocked", "hh_disabled_4a": "blocked", "hh_families_type_6a": "blocked", "hh_family_composition_6a": "blocked", "hh_multi_language_3a": {"count": [2851, 780], "percent": [78.5, 21.5]}, "hh_size_5a": "blocked", "hh_tenure_5a": "blocked", "highest_qualification": "blocked", "hours_per_week_worked": "blocked", "is_carer_5a": "blocked", "legal_partnership_status_6a": "blocked", "national_identity_all_4a": "blocked", "ns_sec_10a": "blocked", "number_bedrooms_5a": "blocked", "number_of_cars_5a": "blocked", "occupancy_rating_bedrooms_6a": "blocked", "occupation_current_10a": "blocked", "passports_all_4a": "blocked", "religion_tb": "blocked", "resident_age_18b": {"count": [0, 0, 0, 0, 0, 0, 0, 3714, 0, 0, 0, 0, 0, 0, 0, 0, 0, 0], "percent": [0.0, 0.0, 0.0, 0.0, 0.0, 0.0, 0.0, 100.0, 0.0, 0.0, 0.0, 0.0, 0.0, 0.0, 0.0, 0.0, 0.0, 0.0]}, "resident_age_23a": {"count": [0, 0, 0, 0, 0, 0, 0, 3714, 0, 0, 0, 0, 0, 0, 0, 0, 0, 0], "percent": [0.0, 0.0, 0.0, 0.0, 0.0, 0.0, 0.0, 100.0, 0.0, 0.0, 0.0, 0.0, 0.0, 0.0, 0.0, 0.0, 0.0, 0.0]}, "sex": {"count": [2144, 1569], "percent": [57.7, 42.3]}, "transport_to_workplace_12a": "blocked", "workplace_travel_8a": "blocked", "total_pop": {"count": 3714, "percent": 0.0}}, "9": {"accommodation_type_3a": "blocked", "country_of_birth_3a": {"count": [0, 4543], "percent": [0.0, 100.0]}, "disability_3a": {"count": [463, 4082], "percent": [10.2, 89.8]}, "economic_activity_status_4a": "blocked", "english_proficiency": "blocked", "has_ever_worked": "blocked", "health_in_general": "blocked", "heating_type_3a": {"count": [145, 4370], "percent": [3.2, 96.8]}, "hh_dependent_children_3a": {"count": [1313, 3203], "percent": [29.1, 70.9]}, "hh_deprivation": "blocked", "hh_disabled_4a": "blocked", "hh_families_type_6a": "blocked", "hh_family_composition_6a": "blocked", "hh_multi_language_3a": {"count": [3521, 991], "percent": [78.0, 22.0]}, "hh_size_5a": "blocked", "hh_tenure_5a": "blocked", "highest_qualification": "blocked", "hours_per_week_worked": "blocked", "is_carer_5a": "blocked", "legal_partnership_status_6a": "blocked", "national_identity_all_4a": "blocked", "ns_sec_10a": "blocked", "number_bedrooms_5a": "blocked", "number_of_cars_5a": "blocked", "occupancy_rating_bedrooms_6a": "blocked", "occupation_current_10a": "blocked", "passports_all_4a": "blocked", "religion_tb": "blocked", "resident_age_18b": {"count": [0, 0, 0, 0, 0, 0, 0, 0, 4543, 0, 0, 0, 0, 0, 0, 0, 0, 0], "percent": [0.0, 0.0, 0.0, 0.0, 0.0, 0.0, 0.0, 0.0, 100.0, 0.0, 0.0, 0.0, 0.0, 0.0, 0.0, 0.0, 0.0, 0.0]}, "resident_age_23a": {"count": [0, 0, 0, 0, 0, 0, 0, 0, 4543, 0, 0, 0, 0, 0, 0, 0, 0, 0], "percent": [0.0, 0.0, 0.0, 0.0, 0.0, 0.0, 0.0, 0.0, 100.0, 0.0, 0.0, 0.0, 0.0, 0.0, 0.0, 0.0, 0.0, 0.0]}, "sex": {"count": [2571, 1972], "percent": [56.6, 43.4]}, "transport_to_workplace_12a": "blocked", "workplace_travel_8a": "blocked", "total_pop": {"count": 4543, "percent": 0.0}}, "10": {"accommodation_type_3a": "blocked", "country_of_birth_3a": {"count": [0, 4107], "percent": [0.0, 100.0]}, "disability_3a": {"count": [487, 3620], "percent": [11.9, 88.1]}, "economic_activity_status_4a": "blocked", "english_proficiency": "blocked", "has_ever_worked": "blocked", "health_in_general": "blocked", "heating_type_3a": {"count": [119, 3966], "percent": [2.9, 97.1]}, "hh_dependent_children_3a": {"count": [1398, 2688], "percent": [34.2, 65.8]}, "hh_deprivation": "blocked", "hh_disabled_4a": "blocked", "hh_families_type_6a": "blocked", "hh_family_composition_6a": "blocked", "hh_multi_language_3a": {"count": [3095, 991], "percent": [75.7, 24.3]}, "hh_size_5a": "blocked", "hh_tenure_5a": "blocked", "highest_qualification": "blocked", "hours_per_week_worked": "blocked", "is_carer_5a": "blocked", "legal_partnership_status_6a": "blocked", "national_identity_all_4a": "blocked", "ns_sec_10a": "blocked", "number_bedrooms_5a": "blocked", "number_of_cars_5a": "blocked", "occupancy_rating_bedrooms_6a": "blocked", "occupation_current_10a": "blocked", "passports_all_4a": "blocked", "religion_tb": "blocked", "resident_age_18b": {"count": [0, 0, 0, 0, 0, 0, 0, 0, 0, 4107, 0, 0, 0, 0, 0, 0, 0, 0], "percent": [0.0, 0.0, 0.0, 0.0, 0.0, 0.0, 0.0, 0.0, 0.0, 100.0, 0.0, 0.0, 0.0, 0.0, 0.0, 0.0, 0.0, 0.0]}, "resident_age_23a": {"count": [0, 0, 0, 0, 0, 0, 0, 0, 0, 4107, 0, 0, 0, 0, 0, 0, 0, 0], "percent": [0.0, 0.0, 0.0, 0.0, 0.0, 0.0, 0.0, 0.0, 0.0, 100.0, 0.0, 0.0, 0.0, 0.0, 0.0, 0.0, 0.0, 0.0]}, "sex": {"count": [2368, 1739], "percent": [57.7, 42.3]}, "transport_to_workplace_12a": "blocked", "workplace_travel_8a": "blocked", "total_pop": {"count": 4107, "percent": 0.0}}, "11": {"accommodation_type_3a": "blocked", "country_of_birth_3a": {"count": [0, 4085], "percent": [0.0, 100.0]}, "disability_3a": {"count": [677, 3408], "percent": [16.6, 83.4]}, "economic_activity_status_4a": "blocked", "english_proficiency": "blocked", "has_ever_worked": "blocked", "health_in_general": "blocked", "heating_type_3a": {"count": [129, 3920], "percent": [3.2, 96.8]}, "hh_dependent_children_3a": {"count": [2094, 1955], "percent": [51.7, 48.3]}, "hh_deprivation": "blocked", "hh_disabled_4a": "blocked", "hh_families_type_6a": "blocked", "hh_family_composition_6a": "blocked", "hh_multi_language_3a": {"count": [3255, 794], "percent": [80.4, 19.6]}, "hh_size_5a": "blocked", "hh_tenure_5a": "blocked", "highest_qualification": "blocked", "hours_per_week_worked": "blocked", "is_carer_5a": "blocked", "legal_partnership_status_6a": "blocked", "national_identity_all_4a": "blocked", "ns_sec_10a": "blocked", "number_bedrooms_5a": "blocked", "number_of_cars_5a": "blocked", "occupancy_rating_bedrooms_6a": "blocked", "occupation_current_10a": "blocked", "passports_all_4a": "blocked", "religion_tb": "blocked", "resident_age_18b": {"count": [0, 0, 0, 0, 0, 0, 0, 0, 0, 0, 4085, 0, 0, 0, 0, 0, 0, 0], "percent": [0.0, 0.0, 0.0, 0.0, 0.0, 0.0, 0.0, 0.0, 0.0, 0.0, 100.0, 0.0, 0.0, 0.0, 0.0, 0.0, 0.0, 0.0]}, "resident_age_23a": {"count": [0, 0, 0, 0, 0, 0, 0, 0, 0, 0, 4085, 0, 0, 0, 0, 0, 0, 0], "percent": [0.0, 0.0, 0.0, 0.0, 0.0, 0.0, 0.0, 0.0, 0.0, 0.0, 100.0, 0.0, 0.0, 0.0, 0.0, 0.0, 0.0, 0.0]}, "sex": {"count": [2375, 1710], "percent": [58.1, 41.9]}, "transport_to_workplace_12a": "blocked", "workplace_travel_8a": "blocked", "total_pop": {"count": 4085, "percent": 0.0}}, "12": {"accommodation_type_3a": "blocked", "country_of_birth_3a": {"count": [0, 3360], "percent": [0.0, 100.0]}, "disability_3a": {"count": [671, 2690], "percent": [20.0, 80.0]}, "economic_activity_status_4a": "blocked", "english_proficiency": "blocked", "has_ever_worked": "blocked", "health_in_general": "blocked", "heating_type_3a": {"count": [92, 3232], "percent": [2.8, 97.2]}, "hh_dependent_children_3a": {"count": [2355, 969], "percent": [70.8, 29.2]}, "hh_deprivation": "blocked", "hh_disabled_4a": "blocked", "hh_families_type_6a": "blocked", "hh_family_composition_6a": "blocked", "hh_multi_language_3a": {"count": [2726, 598], "percent": [82.0, 18.0]}, "hh_size_5a": "blocked", "hh_tenure_5a": "blocked", "highest_qualification": "blocked", "hours_per_week_worked": "blocked", "is_carer_5a": "blocked", "legal_partnership_status_6a": "blocked", "national_identity_all_4a": "blocked", "ns_sec_10a": "blocked", "number_bedrooms_5a": "blocked", "number_of_cars_5a": "blocked", "occupancy_rating_bedrooms_6a": "blocked", "occupation_current_10a": "blocked", "passports_all_4a": "blocked", "religion_tb": "blocked", "resident_age_18b": {"count": [0, 0, 0, 0, 0, 0, 0, 0, 0, 0, 0, 3360, 0, 0, 0, 0, 0, 0], "percent": [0.0, 0.0, 0.0, 0.0, 0.0, 0.0, 0.0, 0.0, 0.0, 0.0, 0.0, 100.0, 0.0, 0.0, 0.0, 0.0, 0.0, 0.0]}, "resident_age_23a": {"count": [0, 0, 0, 0, 0, 0, 0, 0, 0, 0, 0, 3360, 0, 0, 0, 0, 0, 0], "percent": [0.0, 0.0, 0.0, 0.0, 0.0, 0.0, 0.0, 0.0, 0.0, 0.0, 0.0, 100.0, 0.0, 0.0, 0.0, 0.0, 0.0, 0.0]}, "sex": {"count": [1841, 1518], "percent": [54.8, 45.2]}, "transport_to_workplace_12a": "blocked", "workplace_travel_8a": "blocked", "total_pop": {"count": 3360, "percent": 0.0}}, "13": {"accommodation_type_3a": "blocked", "country_of_birth_3a": {"count": [0, 4206], "percent": [0.0, 100.0]}, "disability_3a": {"count": [1128, 3078], "percent": [26.8, 73.2]}, "economic_activity_status_4a": "blocked", "english_proficiency": "blocked", "has_ever_worked": "blocked", "health_in_general": "blocked", "heating_type_3a": {"count": [95, 4058], "percent": [2.3, 97.7]}, "hh_dependent_children_3a": {"count": [3569, 585], "percent": [85.9, 14.1]}, "hh_deprivation": "blocked", "hh_disabled_4a": "blocked", "hh_families_type_6a": "blocked", "hh_family_composition_6a": "blocked", "hh_multi_language_3a": {"count": [3769, 384], "percent": [90.8, 9.2]}, "hh_size_5a": "blocked", "hh_tenure_5a": "blocked", "highest_qualification": "blocked", "hours_per_week_worked": "blocked", "is_carer_5a": "blocked", "legal_partnership_status_6a": "blocked", "national_identity_all_4a": "blocked", "ns_sec_10a": "blocked", "number_bedrooms_5a": "blocked", "number_of_cars_5a": "blocked", "occupancy_rating_bedrooms_6a": "blocked", "occupation_current_10a": "blocked", "passports_all_4a": "blocked", "religion_tb": "blocked", "resident_age_18b": {"count": [0, 0, 0, 0, 0, 0, 0, 0, 0, 0, 0, 0, 4206, 0, 0, 0, 0, 0], "percent": [0.0, 0.0, 0.0, 0.0, 0.0, 0.0, 0.0, 0.0, 0.0, 0.0, 0.0, 0.0, 100.0, 0.0, 0.0, 0.0, 0.0, 0.0]}, "resident_age_23a": {"count": [0, 0, 0, 0, 0, 0, 0, 0, 0, 0, 0, 0, 4206, 0, 0, 0, 0, 0], "percent": [0.0, 0.0, 0.0, 0.0, 0.0, 0.0, 0.0, 0.0, 0.0, 0.0, 0.0, 0.0, 100.0, 0.0, 0.0, 0.0, 0.0, 0.0]}, "sex": {"count": [2395, 1811], "percent": [56.9, 43.1]}, "transport_to_workplace_12a": "blocked", "workplace_travel_8a": "blocked", "total_pop": {"count": 4206, "percent": 0.0}}, "14": {"accommodation_type_3a": "blocked", "country_of_birth_3a": {"count": [0, 3226], "percent": [0.0, 100.0]}, "disability_3a": {"count": [928, 2298], "percent": [28.8, 71.2]}, "economic_activity_status_4a": "blocked", "english_proficiency": "blocked", "has_ever_worked": "blocked", "health_in_general": "blocked", "heating_type_3a": {"count": [71, 3126], "percent": [2.2, 97.8]}, "hh_dependent_children_3a": {"count": [2943, 254], "percent": [92.1, 7.9]}, "hh_deprivation": "blocked", "hh_disabled_4a": "blocked", "hh_families_type_6a": "blocked", "hh_family_composition_6a": "blocked", "hh_multi_language_3a": {"count": [3028, 169], "percent": [94.7, 5.3]}, "hh_size_5a": "blocked", "hh_tenure_5a": "blocked", "highest_qualification": "blocked", "hours_per_week_worked": "blocked", "is_carer_5a": "blocked", "legal_partnership_status_6a": "blocked", "national_identity_all_4a": "blocked", "ns_sec_10a": "blocked", "number_bedrooms_5a": "blocked", "number_of_cars_5a": "blocked", "occupancy_rating_bedrooms_6a": "blocked", "occupation_current_10a": "blocked", "passports_all_4a": "blocked", "religion_tb": "blocked", "resident_age_18b": {"count": [0, 0, 0, 0, 0, 0, 0, 0, 0, 0, 0, 0, 0, 3226, 0, 0, 0, 0], "percent": [0.0, 0.0, 0.0, 0.0, 0.0, 0.0, 0.0, 0.0, 0.0, 0.0, 0.0, 0.0, 0.0, 100.0, 0.0, 0.0, 0.0, 0.0]}, "resident_age_23a": {"count": [0, 0, 0, 0, 0, 0, 0, 0, 0, 0, 0, 0, 0, 3226, 0, 0, 0, 0], "percent": [0.0, 0.0, 0.0, 0.0, 0.0, 0.0, 0.0, 0.0, 0.0, 0.0, 0.0, 0.0, 0.0, 100.0, 0.0, 0.0, 0.0, 0.0]}, "sex": {"count": [1876, 1350], "percent": [58.2, 41.8]}, "transport_to_workplace_12a": "blocked", "workplace_travel_8a": "blocked", "total_pop": {"count": 3226, "percent": 0.0}}, "15": {"accommodation_type_3a": "blocked", "country_of_birth_3a": {"count": [0, 2122], "percent": [0.0, 100.0]}, "disability_3a": {"count": [640, 1482], "percent": [30.2, 69.8]}, "economic_activity_status_4a": "blocked", "english_proficiency": "blocked", "has_ever_worked": "blocked", "health_in_general": "blocked", "heating_type_3a": {"count": [33, 2066], "percent": [1.6, 98.4]}, "hh_dependent_children_3a": {"count": [1971, 128], "percent": [93.9, 6.1]}, "hh_deprivation": "blocked", "hh_disabled_4a": "blocked", "hh_families_type_6a": "blocked", "hh_family_composition_6a": "blocked", "hh_multi_language_3a": {"count": [1980, 119], "percent": [94.3, 5.7]}, "hh_size_5a": "blocked", "hh_tenure_5a": "blocked", "highest_qualification": "blocked", "hours_per_week_worked": "blocked", "is_carer_5a": "blocked", "legal_partnership_status_6a": "blocked", "national_identity_all_4a": "blocked", "ns_sec_10a": "blocked", "number_bedrooms_5a": "blocked", "number_of_cars_5a": "blocked", "occupancy_rating_bedrooms_6a": "blocked", "occupation_current_10a": "blocked", "passports_all_4a": "blocked", "religion_tb": "blocked", "resident_age_18b": {"count": [0, 0, 0, 0, 0, 0, 0, 0, 0, 0, 0, 0, 0, 0, 2122, 0, 0, 0], "percent": [0.0, 0.0, 0.0, 0.0, 0.0, 0.0, 0.0, 0.0, 0.0, 0.0, 0.0, 0.0, 0.0, 0.0, 100.0, 0.0, 0.0, 0.0]}, "resident_age_23a": {"count": [0, 0, 0, 0, 0, 0, 0, 0, 0, 0, 0, 0, 0, 0, 2122, 0, 0, 0], "percent": [0.0, 0.0, 0.0, 0.0, 0.0, 0.0, 0.0, 0.0, 0.0, 0.0, 0.0, 0.0, 0.0, 0.0, 100.0, 0.0, 0.0, 0.0]}, "sex": {"count": [1340, 782], "percent": [63.1, 36.9]}, "transport_to_workplace_12a": "blocked", "workplace_travel_8a": "blocked", "total_pop": {"count": 2122, "percent": 0.0}}, "16": {"accommodation_type_3a": "blocked", "country_of_birth_3a": {"count": [0, 1842], "percent": [0.0, 100.0]}, "disability_3a": {"count": [665, 1177], "percent": [36.1, 63.9]}, "economic_activity_status_4a": "blocked", "english_proficiency": "blocked", "has_ever_worked": "blocked", "health_in_general": "blocked", "heating_type_3a": {"count": [50, 1752], "percent": [2.8, 97.2]}, "hh_dependent_children_3a": {"count": [1723, 79], "percent": [95.6, 4.4]}, "hh_deprivation": "blocked", "hh_disabled_4a": "blocked", "hh_families_type_6a": "blocked", "hh_family_composition_6a": "blocked", "hh_multi_language_3a": {"count": [1734, 68], "percent": [96.2, 3.8]}, "hh_size_5a": "blocked", "hh_tenure_5a": "blocked", "highest_qualification": "blocked", "hours_per_week_worked": "blocked", "is_carer_5a": "blocked", "legal_partnership_status_6a": "blocked", "national_identity_all_4a": "blocked", "ns_sec_10a": "blocked", "number_bedrooms_5a": "blocked", "number_of_cars_5a": "blocked", "occupancy_rating_bedrooms_6a": "blocked", "occupation_current_10a": "blocked", "passports_all_4a": "blocked", "religion_tb": "blocked", "resident_age_18b": {"count": [0, 0, 0, 0, 0, 0, 0, 0, 0, 0, 0, 0, 0, 0, 0, 1842, 0, 0], "percent": [0.0, 0.0, 0.0, 0.0, 0.0, 0.0, 0.0, 0.0, 0.0, 0.0, 0.0, 0.0, 0.0, 0.0, 0.0, 100.0, 0.0, 0.0]}, "resident_age_23a": {"count": [0, 0, 0, 0, 0, 0, 0, 0, 0, 0, 0, 0, 0, 0, 0, 1842, 0, 0], "percent": [0.0, 0.0, 0.0, 0.0, 0.0, 0.0, 0.0, 0.0, 0.0, 0.0, 0.0, 0.0, 0.0, 0.0, 0.0, 100.0, 0.0, 0.0]}, "sex": {"count": [1115, 727], "percent": [60.5, 39.5]}, "transport_to_workplace_12a": "blocked", "workplace_travel_8a": "blocked", "total_pop": {"count": 1842, "percent": 0.0}}, "17": {"accommodation_type_3a": "blocked", "country_of_birth_3a": {"count": [0, 1622], "percent": [0.0, 100.0]}, "disability_3a": {"count": [725, 897], "percent": [44.7, 55.3]}, "economic_activity_status_4a": "blocked", "english_proficiency": "blocked", "has_ever_worked": "blocked", "health_in_general": "blocked", "heating_type_3a": {"count": [41, 1559], "percent": [2.6, 97.4]}, "hh_dependent_children_3a": {"count": [1489, 109], "percent": [93.2, 6.8]}, "hh_deprivation": "blocked", "hh_disabled_4a": "blocked", "hh_families_type_6a": "blocked", "hh_family_composition_6a": "blocked", "hh_multi_language_3a": {"count": [1526, 73], "percent": [95.4, 4.6]}, "hh_size_5a": "blocked", "hh_tenure_5a": "blocked", "highest_qualification": "blocked", "hours_per_week_worked": "blocked", "is_carer_5a": "blocked", "legal_partnership_status_6a": "blocked", "national_identity_all_4a": "blocked", "ns_sec_10a": "blocked", "number_bedrooms_5a": "blocked", "number_of_cars_5a": "blocked", "occupancy_rating_bedrooms_6a": "blocked", "occupation_current_10a": "blocked", "passports_all_4a": "blocked", "religion_tb": "blocked", "resident_age_18b": {"count": [0, 0, 0, 0, 0, 0, 0, 0, 0, 0, 0, 0, 0, 0, 0, 0, 1622, 0], "percent": [0.0, 0.0, 0.0, 0.0, 0.0, 0.0, 0.0, 0.0, 0.0, 0.0, 0.0, 0.0, 0.0, 0.0, 0.0, 0.0, 100.0, 0.0]}, "resident_age_23a": {"count": [0, 0, 0, 0, 0, 0, 0, 0, 0, 0, 0, 0, 0, 0, 0, 0, 1622, 0], "percent": [0.0, 0.0, 0.0, 0.0, 0.0, 0.0, 0.0, 0.0, 0.0, 0.0, 0.0, 0.0, 0.0, 0.0, 0.0, 0.0, 100.0, 0.0]}, "sex": {"count": [934, 688], "percent": [57.6, 42.4]}, "transport_to_workplace_12a": "blocked", "workplace_travel_8a": "blocked", "total_pop": {"count": 1622, "percent": 0.0}}, "18": {"accommodation_type_3a": "blocked", "country_of_birth_3a": {"count": [0, 1064], "percent": [0.0, 100.0]}, "disability_3a": {"count": [605, 459], "percent": [56.9, 43.1]}, "economic_activity_status_4a": "blocked", "english_proficiency": "blocked", "has_ever_worked": "blocked", "health_in_general": "blocked", "heating_type_3a": {"count": [26, 977], "percent": [2.6, 97.4]}, "hh_dependent_children_3a": {"count": [956, 44], "percent": [95.6, 4.4]}, "hh_deprivation": "blocked", "hh_disabled_4a": "blocked", "hh_families_type_6a": "blocked", "hh_family_composition_6a": "blocked", "hh_multi_language_3a": {"count": [961, 42], "percent": [95.8, 4.2]}, "hh_size_5a": "blocked", "hh_tenure_5a": "blocked", "highest_qualification": "blocked", "hours_per_week_worked": "blocked", "is_carer_5a": "blocked", "legal_partnership_status_6a": "blocked", "national_identity_all_4a": "blocked", "ns_sec_10a": "blocked", "number_bedrooms_5a": "blocked", "number_of_cars_5a": "blocked", "occupancy_rating_bedrooms_6a": "blocked", "occupation_current_10a": "blocked", "passports_all_4a": "blocked", "religion_tb": "blocked", "resident_age_18b": {"count": [0, 0, 0, 0, 0, 0, 0, 0, 0, 0, 0, 0, 0, 0, 0, 0, 0, 1064], "percent": [0.0, 0.0, 0.0, 0.0, 0.0, 0.0, 0.0, 0.0, 0.0, 0.0, 0.0, 0.0, 0.0, 0.0, 0.0, 0.0, 0.0, 100.0]}, "resident_age_23a": {"count": [0, 0, 0, 0, 0, 0, 0, 0, 0, 0, 0, 0, 0, 0, 0, 0, 0, 1064], "percent": [0.0, 0.0, 0.0, 0.0, 0.0, 0.0, 0.0, 0.0, 0.0, 0.0, 0.0, 0.0, 0.0, 0.0, 0.0, 0.0, 0.0, 100.0]}, "sex": {"count": [635, 429], "percent": [59.7, 40.3]}, "transport_to_workplace_12a": "blocked", "workplace_travel_8a": "blocked", "total_pop": {"count": 1064, "percent": 0.0}}}, "map_data": {"1": {"E06000035": [0, 0.0], "E06000042": [0, 0.0], "E06000043": [0, 0.0], "E08000003": [0, 0.0], "E08000012": [0, 0.0], "E08000025": [0, 0.0], "E08000035": [0, 0.0], "E09000005": [0, 0.0], "E09000006": [0, 0.0], "E09000008": [0, 0.0], "E09000009": [0, 0.0], "E09000010": [0, 0.0], "E09000011": [0, 0.0], "E09000015": [0, 0.0], "E09000017": [0, 0.0], "E09000018": [0, 0.0], "E09000019": [0, 0.0], "E09000022": [0, 0.0], "E09000028": [0, 0.0], "E09000032": [0, 0.0], "E09000033": [0, 0.0], "W06000015": [0, 0.0]}, "2": {"E06000035": [0, 0.0], "E06000042": [0, 0.0], "E06000043": [0, 0.0], "E08000003": [0, 0.0], "E08000012": [0, 0.0], "E08000025": [0, 0.0], "E08000035": [0, 0.0], "E09000005": [0, 0.0], "E09000006": [0, 0.0], "E09000008": [0, 0.0], "E09000009": [0, 0.0], "E09000010": [0, 0.0], "E09000011": [0, 0.0], "E09000015": [0, 0.0], "E09000017": [0, 0.0], "E09000018": [0, 0.0], "E09000019": [0, 0.0], "E09000022": [0, 0.0], "E09000028": [0, 0.0], "E09000032": [0, 0.0], "E09000033": [0, 0.0], "W06000015": [0, 0.0]}, "3": {"E06000035": [5, 0.0], "E06000042": [16, 0.0], "E06000043": [1, 0.0], "E08000003": [35, 0.0], "E08000012": [5, 0.0], "E08000025": [16, 0.0], "E08000035": [17, 0.0], "E09000005": [7, 0.0], "E09000006": [12, 0.0], "E09000008": [15, 0.0], "E09000009": [3, 0.0], "E09000010": [9, 0.0], "E09000011": [41, 0.0], "E09000015": [3, 0.0], "E09000017": [2, 0.0], "E09000018": [4, 0.0], "E09000019": [1, 0.0], "E09000022": [13, 0.0], "E09000028": [15, 0.0], "E09000032": [2, 0.0], "E09000033": [3, 0.0], "W06000015": [5, 0.0]}, "4": {"E06000035": [9, 0.0], "E06000042": [43, 0.0], "E06000043": [3, 0.0], "E08000003": [86, 0.0], "E08000012": [13, 0.0], "E08000025": [89, 0.0], "E08000035": [49, 0.0], "E09000005": [17, 0.0], "E09000006": [5, 0.0], "E09000008": [26, 0.0], "E09000009": [20, 0.0], "E09000010": [28, 0.0], "E09000011": [46, 0.0], "E09000015": [6, 0.0], "E09000017": [17, 0.0], "E09000018": [33, 0.0], "E09000019": [6, 0.0], "E09000022": [29, 0.0], "E09000028": [51, 0.0], "E09000032": [17, 0.0], "E09000033": [3, 0.0], "W06000015": [37, 0.0]}, "5": {"E06000035": [10, 0.0], "E06000042": [48, 0.0], "E06000043": [10, 0.0], "E08000003": [103, 0.0], "E08000012": [22, 0.0], "E08000025": [143, 0.0], "E08000035": [64, 0.0], "E09000005": [33, 0.0], "E09000006": [9, 0.0], "E09000008": [54, 0.0], "E09000009": [36, 0.0], "E09000010": [55, 0.0], "E09000011": [80, 0.0], "E09000015": [16, 0.0], "E09000017": [30, 0.0], "E09000018": [22, 0.0], "E09000019": [12, 0.0], "E09000022": [55, 0.0], "E09000028": [46, 0.0], "E09000032": [30, 0.0], "E09000033": [8, 0.0], "W06000015": [62, 0.0]}, "6": {"E06000035": [19, 0.0], "E06000042": [52, 0.0], "E06000043": [6, 0.0], "E08000003": [105, 0.0], "E08000012": [29, 0.0], "E08000025": [106, 0.0], "E08000035": [50, 0.0], "E09000005": [36, 0.0], "E09000006": [17, 0.0], "E09000008": [69, 0.0], "E09000009": [32, 0.0], "E09000010": [43, 0.0], "E09000011": [73, 0.0], "E09000015": [31, 0.0], "E09000017": [27, 0.0], "E09000018": [22, 0.0], "E09000019": [34, 0.0], "E09000022": [53, 0.0], "E09000028": [78, 0.0], "E09000032": [31, 0.0], "E09000033": [12, 0.0], "W06000015": [24, 0.0]}, "7": {"E06000035": [22, 0.0], "E06000042": [38, 0.0], "E06000043": [6, 0.0], "E08000003": [97, 0.0], "E08000012": [23, 0.0], "E08000025": [115, 0.0], "E08000035": [68, 0.0], "E09000005": [48, 0.0], "E09000006": [28, 0.0], "E09000008": [82, 0.0], "E09000009": [37, 0.0], "E09000010": [44, 0.0], "E09000011": [56, 0.0], "E09000015": [21, 0.0], "E09000017": [27, 0.0], "E09000018": [54, 0.0], "E09000019": [41, 0.0], "E09000022": [62, 0.0], "E09000028": [137, 0.0], "E09000032": [43, 0.0], "E09000033": [13, 0.0], "W06000015": [11, 0.0]}, "8": {"E06000035": [17, 0.0], "E06000042": [44, 0.0], "E06000043": [8, 0.0], "E08000003": [120, 0.0], "E08000012": [34, 0.0], "E08000025": [127, 0.0], "E08000035": [70, 0.0], "E09000005": [60, 0.0], "E09000006": [45, 0.0], "E09000008": [107, 0.0], "E09000009": [36, 0.0], "E09000010": [67, 0.0], "E09000011": [109, 0.0], "E09000015": [22, 0.0], "E09000017": [30, 0.0], "E09000018": [54, 0.0], "E09000019": [40, 0.0], "E09000022": [89, 0.0], "E09000028": [117, 0.0], "E09000032": [31, 0.0], "E09000033": [18, 0.0], "W06000015": [39, 0.0]}, "9": {"E06000035": [42, 0.0], "E06000042": [72, 0.0], "E06000043": [11, 0.0], "E08000003": [97, 0.0], "E08000012": [43, 0.0], "E08000025": [123, 0.0], "E08000035": [98, 0.0], "E09000005": [69, 0.0], "E09000006": [63, 0.0], "E09000008": [134, 0.0], "E09000009": [63, 0.0], "E09000010": [68, 0.0], "E09000011": [133, 0.0], "E09000015": [20, 0.0], "E09000017": [39, 0.0], "E09000018": [42, 0.0], "E09000019": [28, 0.0], "E09000022": [91, 0.0], "E09000028": [114, 0.0], "E09000032": [54, 0.0], "E09000033": [36, 0.0], "W06000015": [45, 0.0]}, "10": {"E06000035": [36, 0.0], "E06000042": [59, 0.0], "E06000043": [8, 0.0], "E08000003": [119, 0.0], "E08000012": [40, 0.0], "E08000025": [130, 0.0], "E08000035": [87, 0.0], "E09000005": [72, 0.0], "E09000006": [40, 0.0], "E09000008": [107, 0.0], "E09000009": [60, 0.0], "E09000010": [63, 0.0], "E09000011": [123, 0.0], "E09000015": [24, 0.0], "E09000017": [42, 0.0], "E09000018": [50, 0.0], "E09000019": [45, 0.0], "E09000022": [102, 0.0], "E09000028": [151, 0.0], "E09000032": [61, 0.0], "E09000033": [28, 0.0], "W06000015": [33, 0.0]}, "11": {"E06000035": [16, 0.0], "E06000042": [59, 0.0], "E06000043": [13, 0.0], "E08000003": [99, 0.0], "E08000012": [27, 0.0], "E08000025": [123, 0.0], "E08000035": [44, 0.0], "E09000005": [81, 0.0], "E09000006": [95, 0.0], "E09000008": [118, 0.0], "E09000009": [58, 0.0], "E09000010": [83, 0.0], "E09000011": [140, 0.0], "E09000015": [29, 0.0], "E09000017": [44, 0.0], "E09000018": [37, 0.0], "E09000019": [38, 0.0], "E09000022": [118, 0.0], "E09000028": [213, 0.1], "E09000032": [95, 0.0], "E09000033": [28, 0.0], "W06000015": [29, 0.0]}, "12": {"E06000035": [21, 0.0], "E06000042": [29, 0.0], "E06000043": [10, 0.0], "E08000003": [73, 0.0], "E08000012": [19, 0.0], "E08000025": [99, 0.0], "E08000035": [38, 0.0], "E09000005": [81, 0.0], "E09000006": [35, 0.0], "E09000008": [130, 0.0], "E09000009": [42, 0.0], "E09000010": [98, 0.0], "E09000011": [76, 0.0], "E09000015": [29, 0.0], "E09000017": [28, 0.0], "E09000018": [36, 0.0], "E09000019": [52, 0.0], "E09000022": [110, 0.0], "E09000028": [185, 0.1], "E09000032": [44, 0.0], "E09000033": [21, 0.0], "W06000015": [26, 0.0]}, "13": {"E06000035": [18, 0.0], "E06000042": [31, 0.0], "E06000043": [7, 0.0], "E08000003": [93, 0.0], "E08000012": [15, 0.0], "E08000025": [191, 0.0], "E08000035": [57, 0.0], "E09000005": [130, 0.0], "E09000006": [37, 0.0], "E09000008": [163, 0.0], "E09000009": [64, 0.0], "E09000010": [102, 0.0], "E09000011": [83, 0.0], "E09000015": [45, 0.0], "E09000017": [25, 0.0], "E09000018": [45, 0.0], "E09000019": [47, 0.0], "E09000022": [188, 0.1], "E09000028": [173, 0.1], "E09000032": [121, 0.0], "E09000033": [47, 0.0], "W06000015": [20, 0.0]}, "14": {"E06000035": [10, 0.0], "E06000042": [27, 0.0], "E06000043": [9, 0.0], "E08000003": [60, 0.0], "E08000012": [18, 0.0], "E08000025": [197, 0.0], "E08000035": [55, 0.0], "E09000005": [120, 0.0], "E09000006": [22, 0.0], "E09000008": [147, 0.0], "E09000009": [55, 0.0], "E09000010": [74, 0.0], "E09000011": [62, 0.0], "E09000015": [24, 0.0], "E09000017": [24, 0.0], "E09000018": [20, 0.0], "E09000019": [48, 0.0], "E09000022": [148, 0.0], "E09000028": [119, 0.0], "E09000032": [92, 0.0], "E09000033": [24, 0.0], "W06000015": [12, 0.0]}, "15": {"E06000035": [5, 0.0], "E06000042": [10, 0.0], "E06000043": [6, 0.0], "E08000003": [33, 0.0], "E08000012": [17, 0.0], "E08000025": [95, 0.0], "E08000035": [15, 0.0], "E09000005": [75, 0.0], "E09000006": [16, 0.0], "E09000008": [96, 0.0], "E09000009": [37, 0.0], "E09000010": [64, 0.0], "E09000011": [31, 0.0], "E09000015": [23, 0.0], "E09000017": [20, 0.0], "E09000018": [14, 0.0], "E09000019": [30, 0.0], "E09000022": [107, 0.0], "E09000028": [71, 0.0], "E09000032": [48, 0.0], "E09000033": [19, 0.0], "W06000015": [11, 0.0]}, "16": {"E06000035": [11, 0.0], "E06000042": [15, 0.0], "E06000043": [6, 0.0], "E08000003": [17, 0.0], "E08000012": [10, 0.0], "E08000025": [86, 0.0], "E08000035": [15, 0.0], "E09000005": [87, 0.0], "E09000006": [22, 0.0], "E09000008": [84, 0.0], "E09000009": [40, 0.0], "E09000010": [48, 0.0], "E09000011": [30, 0.0], "E09000015": [23, 0.0], "E09000017": [25, 0.0], "E09000018": [20, 0.0], "E09000019": [22, 0.0], "E09000022": [81, 0.0], "E09000028": [67, 0.0], "E09000032": [39, 0.0], "E09000033": [20, 0.0], "W06000015": [11, 0.0]}, "17": {"E06000035": [5, 0.0], "E06000042": [11, 0.0], "E06000043": [2, 0.0], "E08000003": [28, 0.0], "E08000012": [7, 0.0], "E08000025": [94, 0.0], "E08000035": [17, 0.0], "E09000005": [59, 0.0], "E09000006": [9, 0.0], "E09000008": [72, 0.0], "E09000009": [43, 0.0], "E09000010": [38, 0.0], "E09000011": [20, 0.0], "E09000015": [18, 0.0], "E09000017": [13, 0.0], "E09000018": [15, 0.0], "E09000019": [28, 0.0], "E09000022": [76, 0.0], "E09000028": [72, 0.0], "E09000032": [47, 0.0], "E09000033": [22, 0.0], "W06000015": [8, 0.0]}, "18": {"E06000035": [0, 0.0], "E06000042": [7, 0.0], "E06000043": [1, 0.0], "E08000003": [11, 0.0], "E08000012": [5, 0.0], "E08000025": [72, 0.0], "E08000035": [13, 0.0], "E09000005": [55, 0.0], "E09000006": [8, 0.0], "E09000008": [54, 0.0], "E09000009": [25, 0.0], "E09000010": [24, 0.0], "E09000011": [12, 0.0], "E09000015": [13, 0.0], "E09000017": [7, 0.0], "E09000018": [9, 0.0], "E09000019": [16, 0.0], "E09000022": [55, 0.0], "E09000028": [33, 0.0], "E09000032": [36, 0.0], "E09000033": [14, 0.0], "W06000015": [1, 0.0]}}}