{"bar_chart_data": {"1": {"accommodation_type_3a": {"count": [29590, 9817, 190], "percent": [74.7, 24.8, 0.5]}, "country_of_birth_3a": {"count": [33178, 6948], "percent": [82.7, 17.3]}, "disability_3a": {"count": [13244, 26881], "percent": [33.0, 67.0]}, "economic_activity_status_4a": {"count": [22568, 1474, 14745], "percent": [58.2, 3.8, 38.0]}, "english_proficiency": {"count": [37659, 1503, 622, 152, 19], "percent": [94.3, 3.8, 1.6, 0.4, 0.0]}, "has_ever_worked": {"count": [2463, 11689, 2067], "percent": [15.2, 72.1, 12.7]}, "health_in_general": {"count": [15165, 14060, 6859, 3034, 1008], "percent": [37.8, 35.0, 17.1, 7.6, 2.5]}, "heating_type_3a": {"count": [740, 38857], "percent": [1.9, 98.1]}, "hh_dependent_children_3a": {"count": [29191, 10406], "percent": [73.7, 26.3]}, "hh_deprivation": {"count": [17812, 14544, 5979, 1205, 57], "percent": [45.0, 36.7, 15.1, 3.0, 0.1]}, "hh_disabled_4a": {"count": [22046, 13132, 4419], "percent": [55.7, 33.2, 11.2]}, "hh_families_type_6a": {"count": [10943, 13477, 6493, 6222, 2462], "percent": [27.6, 34.0, 16.4, 15.7, 6.2]}, "hh_family_composition_6a": {"count": [10943, 23591, 5063], "percent": [27.6, 59.6, 12.8]}, "hh_multi_language_3a": {"count": [37100, 2497], "percent": [93.7, 6.3]}, "hh_size_5a": {"count": [10943, 14766, 6936, 6952], "percent": [27.6, 37.3, 17.5, 17.6]}, "hh_tenure_5a": {"count": [12022, 11683, 6134, 9758], "percent": [30.4, 29.5, 15.5, 24.6]}, "highest_qualification": {"count": [2500, 11998, 694, 22948, 647], "percent": [6.4, 30.9, 1.8, 59.2, 1.7]}, "hours_per_week_worked": {"count": [4026, 6386, 10468, 1688], "percent": [17.8, 28.3, 46.4, 7.5]}, "is_carer_5a": {"count": [33447, 3700, 1212, 1474], "percent": [84.0, 9.3, 3.0, 3.7]}, "legal_partnership_status_6a": {"count": [15614, 11883, 1466, 8118, 1706], "percent": [40.3, 30.6, 3.8, 20.9, 4.4]}, "national_identity_all_4a": {"count": [33939, 1482, 4705], "percent": [84.6, 3.7, 11.7]}, "ns_sec_10a": {"count": [5541, 11720, 4701, 4844, 931, 4477, 2259, 2241, 2074], "percent": [14.3, 30.2, 12.1, 12.5, 2.4, 11.5, 5.8, 5.8, 5.3]}, "number_bedrooms_5a": {"count": [4954, 11939, 14425, 8279], "percent": [12.5, 30.2, 36.4, 20.9]}, "number_of_cars_5a": {"count": [9050, 17366, 9633, 3548], "percent": [22.9, 43.9, 24.3, 9.0]}, "occupancy_rating_bedrooms_6a": {"count": [12209, 13943, 12012, 1204, 229], "percent": [30.8, 35.2, 30.3, 3.0, 0.6]}, "occupation_current_10a": {"count": [2500, 6602, 4782, 2244, 588, 2999, 1346, 265, 1245], "percent": [11.1, 29.2, 21.2, 9.9, 2.6, 13.3, 6.0, 1.2, 5.5]}, "passports_all_4a": {"count": [32391, 4337, 3398], "percent": [80.7, 10.8, 8.5]}, "residence_length_6b": {"count": [33178, 4540, 1158, 710, 540], "percent": [82.7, 11.3, 2.9, 1.8, 1.3]}, "resident_age_18b": {"count": [291, 402, 529, 890, 1864, 2162, 2697, 3059, 3375, 4122, 4685, 4520, 3518, 3297, 2626, 1251, 538, 297], "percent": [0.7, 1.0, 1.3, 2.2, 4.6, 5.4, 6.7, 7.6, 8.4, 10.3, 11.7, 11.3, 8.8, 8.2, 6.5, 3.1, 1.3, 0.7]}, "resident_age_23a": {"count": [291, 402, 529, 890, 1864, 2162, 2697, 3059, 3375, 4122, 4685, 4520, 3518, 3297, 2626, 1251, 538, 297], "percent": [0.7, 1.0, 1.3, 2.2, 4.6, 5.4, 6.7, 7.6, 8.4, 10.3, 11.7, 11.3, 8.8, 8.2, 6.5, 3.1, 1.3, 0.7]}, "transport_to_workplace_12a": {"count": [10578, 407, 392, 819, 119, 52, 6996, 479, 649, 1831, 242], "percent": [46.9, 1.8, 1.7, 3.6, 0.5, 0.2, 31.0, 2.1, 2.9, 8.1, 1.1]}, "workplace_travel_8a": {"count": [5650, 3246, 1183, 10578, 1908], "percent": [25.0, 14.4, 5.2, 46.9, 8.5]}, "total_pop": {"count": 40126, "percent": 0.1}}, "2": {"accommodation_type_3a": {"count": [31652, 13014, 261], "percent": [70.5, 29.0, 0.6]}, "country_of_birth_3a": {"count": [41064, 5831], "percent": [87.6, 12.4]}, "disability_3a": {"count": [13863, 33032], "percent": [29.6, 70.4]}, "economic_activity_status_4a": {"count": [27322, 2103, 16165], "percent": [59.9, 4.6, 35.5]}, "english_proficiency": {"count": [44736, 1272, 568, 142, 26], "percent": [95.7, 2.7, 1.2, 0.3, 0.1]}, "has_ever_worked": {"count": [2884, 12765, 2619], "percent": [15.8, 69.9, 14.3]}, "health_in_general": {"count": [17197, 16396, 8460, 3567, 1275], "percent": [36.7, 35.0, 18.0, 7.6, 2.7]}, "heating_type_3a": {"count": [1029, 43898], "percent": [2.3, 97.7]}, "hh_dependent_children_3a": {"count": [35301, 9626], "percent": [78.6, 21.4]}, "hh_deprivation": {"count": [20657, 15512, 6880, 1746, 132], "percent": [46.0, 34.5, 15.3, 3.9, 0.3]}, "hh_disabled_4a": {"count": [26294, 14243, 4390], "percent": [58.5, 31.7, 9.8]}, "hh_families_type_6a": {"count": [13051, 17425, 7226, 3629, 3596], "percent": [29.0, 38.8, 16.1, 8.1, 8.0]}, "hh_family_composition_6a": {"count": [13051, 25573, 6303], "percent": [29.0, 56.9, 14.0]}, "hh_multi_language_3a": {"count": [41123, 3804], "percent": [91.5, 8.5]}, "hh_size_5a": {"count": [13051, 15862, 7670, 8344], "percent": [29.0, 35.3, 17.1, 18.6]}, "hh_tenure_5a": {"count": [12792, 13141, 7023, 11971], "percent": [28.5, 29.2, 15.6, 26.6]}, "highest_qualification": {"count": [3863, 15765, 2411, 22746, 805], "percent": [8.5, 34.6, 5.3, 49.9, 1.8]}, "hours_per_week_worked": {"count": [2790, 3997, 16439, 4099], "percent": [10.2, 14.6, 60.2, 15.0]}, "is_carer_5a": {"count": [41264, 3123, 936, 1296], "percent": [88.5, 6.7, 2.0, 2.8]}, "legal_partnership_status_6a": {"count": [20253, 15736, 1553, 6994, 1054], "percent": [44.4, 34.5, 3.4, 15.3, 2.3]}, "national_identity_all_4a": {"count": [41182, 1449, 4264], "percent": [87.8, 3.1, 9.1]}, "ns_sec_10a": {"count": [8718, 10581, 3142, 7203, 2873, 3551, 4587, 3129, 1808], "percent": [19.1, 23.2, 6.9, 15.8, 6.3, 7.8, 10.1, 6.9, 4.0]}, "number_bedrooms_5a": {"count": [7463, 12367, 15267, 9830], "percent": [16.6, 27.5, 34.0, 21.9]}, "number_of_cars_5a": {"count": [10955, 18478, 11376, 4118], "percent": [24.4, 41.1, 25.3, 9.2]}, "occupancy_rating_bedrooms_6a": {"count": [13706, 15461, 14254, 1264, 242], "percent": [30.5, 34.4, 31.7, 2.8, 0.5]}, "occupation_current_10a": {"count": [4107, 7004, 4739, 1224, 3417, 1637, 1169, 1931, 2095], "percent": [15.0, 25.6, 17.3, 4.5, 12.5, 6.0, 4.3, 7.1, 7.7]}, "passports_all_4a": {"count": [37703, 3690, 5502], "percent": [80.4, 7.9, 11.7]}, "residence_length_6b": {"count": [41064, 3585, 1046, 658, 542], "percent": [87.6, 7.6, 2.2, 1.4, 1.2]}, "resident_age_18b": {"count": [276, 422, 506, 798, 1894, 2688, 3474, 3774, 3987, 5092, 5551, 5333, 4220, 3772, 3132, 1236, 487, 257], "percent": [0.6, 0.9, 1.1, 1.7, 4.0, 5.7, 7.4, 8.0, 8.5, 10.9, 11.8, 11.4, 9.0, 8.0, 6.7, 2.6, 1.0, 0.5]}, "resident_age_23a": {"count": [276, 422, 506, 799, 1894, 2688, 3474, 3774, 3987, 5092, 5551, 5333, 4220, 3772, 3132, 1236, 487, 257], "percent": [0.6, 0.9, 1.1, 1.7, 4.0, 5.7, 7.4, 8.0, 8.5, 10.9, 11.8, 11.4, 9.0, 8.0, 6.7, 2.6, 1.0, 0.5]}, "transport_to_workplace_12a": {"count": [10736, 524, 650, 721, 147, 289, 10041, 460, 1404, 1965, 387], "percent": [39.3, 1.9, 2.4, 2.6, 0.5, 1.1, 36.7, 1.7, 5.1, 7.2, 1.4]}, "workplace_travel_8a": {"count": [5964, 3806, 1647, 10736, 5169], "percent": [21.8, 13.9, 6.0, 39.3, 18.9]}, "total_pop": {"count": 46895, "percent": 0.1}}}, "map_data": {"1": {"E06000001": [31, 0.0], "E06000002": [33, 0.0], "E06000003": [82, 0.1], "E06000004": [91, 0.0], "E06000005": [56, 0.1], "E06000006": [61, 0.0], "E06000007": [92, 0.0], "E06000008": [47, 0.0], "E06000009": [88, 0.1], "E06000010": [145, 0.1], "E06000011": [231, 0.1], "E06000012": [82, 0.1], "E06000013": [89, 0.1], "E06000014": [190, 0.1], "E06000015": [101, 0.0], "E06000016": [118, 0.0], "E06000017": [30, 0.1], "E06000018": [194, 0.1], "E06000019": [196, 0.1], "E06000020": [84, 0.0], "E06000021": [91, 0.0], "E06000022": [213, 0.1], "E06000023": [621, 0.1], "E06000024": [173, 0.1], "E06000025": [159, 0.1], "E06000026": [192, 0.1], "E06000027": [151, 0.1], "E06000030": [104, 0.0], "E06000031": [88, 0.0], "E06000032": [47, 0.0], "E06000033": [174, 0.1], "E06000034": [55, 0.0], "E06000035": [139, 0.0], "E06000036": [78, 0.1], "E06000037": [74, 0.0], "E06000038": [97, 0.1], "E06000039": [34, 0.0], "E06000040": [119, 0.1], "E06000041": [69, 0.0], "E06000042": [144, 0.1], "E06000043": [743, 0.3], "E06000044": [162, 0.1], "E06000045": [172, 0.1], "E06000046": [167, 0.1], "E06000047": [240, 0.0], "E06000049": [258, 0.1], "E06000050": [215, 0.1], "E06000051": [303, 0.1], "E06000052": [765, 0.1], "E06000054": [442, 0.1], "E06000055": [102, 0.1], "E06000056": [156, 0.1], "E06000057": [236, 0.1], "E06000058": [414, 0.1], "E06000059": [423, 0.1], "E06000060": [358, 0.1], "E06000061": [218, 0.1], "E06000062": [279, 0.1], "E07000008": [224, 0.2], "E07000009": [63, 0.1], "E07000010": [52, 0.1], "E07000011": [102, 0.1], "E07000012": [175, 0.1], "E07000026": [59, 0.1], "E07000027": [50, 0.1], "E07000028": [94, 0.1], "E07000029": [26, 0.0], "E07000030": [52, 0.1], "E07000031": [206, 0.2], "E07000032": [89, 0.1], "E07000033": [41, 0.1], "E07000034": [52, 0.1], "E07000035": [75, 0.1], "E07000036": [57, 0.1], "E07000037": [103, 0.1], "E07000038": [60, 0.1], "E07000039": [66, 0.1], "E07000040": [156, 0.1], "E07000041": [152, 0.1], "E07000042": [80, 0.1], "E07000043": [96, 0.1], "E07000044": [257, 0.3], "E07000045": [203, 0.2], "E07000046": [68, 0.1], "E07000047": [68, 0.1], "E07000061": [122, 0.1], "E07000062": [178, 0.2], "E07000063": [201, 0.2], "E07000064": [111, 0.1], "E07000065": [164, 0.1], "E07000066": [80, 0.0], "E07000067": [70, 0.0], "E07000068": [49, 0.1], "E07000069": [52, 0.1], "E07000070": [112, 0.1], "E07000071": [176, 0.1], "E07000072": [75, 0.1], "E07000073": [53, 0.1], "E07000074": [50, 0.1], "E07000075": [46, 0.1], "E07000076": [134, 0.1], "E07000077": [71, 0.1], "E07000078": [90, 0.1], "E07000079": [83, 0.1], "E07000080": [58, 0.1], "E07000081": [75, 0.1], "E07000082": [177, 0.1], "E07000083": [56, 0.1], "E07000084": [97, 0.1], "E07000085": [77, 0.1], "E07000086": [81, 0.1], "E07000087": [61, 0.1], "E07000088": [40, 0.0], "E07000089": [66, 0.1], "E07000090": [87, 0.1], "E07000091": [155, 0.1], "E07000092": [41, 0.0], "E07000093": [79, 0.1], "E07000094": [110, 0.1], "E07000095": [55, 0.1], "E07000096": [136, 0.1], "E07000098": [42, 0.0], "E07000099": [103, 0.1], "E07000102": [52, 0.1], "E07000103": [58, 0.1], "E07000105": [95, 0.1], "E07000106": [197, 0.1], "E07000107": [50, 0.0], "E07000108": [125, 0.1], "E07000109": [37, 0.0], "E07000110": [102, 0.1], "E07000111": [74, 0.1], "E07000112": [105, 0.1], "E07000113": [89, 0.1], "E07000114": [176, 0.1], "E07000115": [72, 0.1], "E07000116": [98, 0.1], "E07000117": [48, 0.1], "E07000118": [59, 0.1], "E07000119": [67, 0.1], "E07000120": [37, 0.0], "E07000121": [157, 0.1], "E07000122": [58, 0.1], "E07000123": [64, 0.0], "E07000124": [34, 0.1], "E07000125": [45, 0.1], "E07000126": [67, 0.1], "E07000127": [61, 0.1], "E07000128": [79, 0.1], "E07000129": [43, 0.0], "E07000130": [84, 0.0], "E07000131": [65, 0.1], "E07000132": [65, 0.1], "E07000133": [42, 0.1], "E07000134": [49, 0.0], "E07000135": [21, 0.0], "E07000136": [24, 0.0], "E07000137": [89, 0.1], "E07000138": [61, 0.1], "E07000139": [55, 0.0], "E07000140": [35, 0.0], "E07000141": [69, 0.0], "E07000142": [57, 0.1], "E07000143": [95, 0.1], "E07000144": [83, 0.1], "E07000145": [48, 0.0], "E07000146": [117, 0.1], "E07000147": [126, 0.1], "E07000148": [200, 0.1], "E07000149": [135, 0.1], "E07000163": [54, 0.1], "E07000164": [46, 0.1], "E07000165": [126, 0.1], "E07000166": [25, 0.1], "E07000167": [35, 0.1], "E07000168": [102, 0.1], "E07000169": [44, 0.0], "E07000170": [47, 0.0], "E07000171": [44, 0.0], "E07000172": [68, 0.1], "E07000173": [100, 0.1], "E07000174": [33, 0.0], "E07000175": [65, 0.1], "E07000176": [80, 0.1], "E07000177": [111, 0.1], "E07000178": [187, 0.1], "E07000179": [114, 0.1], "E07000180": [100, 0.1], "E07000181": [104, 0.1], "E07000187": [212, 0.2], "E07000188": [55, 0.0], "E07000189": [161, 0.1], "E07000192": [38, 0.0], "E07000193": [50, 0.0], "E07000194": [53, 0.0], "E07000195": [59, 0.0], "E07000196": [53, 0.0], "E07000197": [81, 0.1], "E07000198": [50, 0.1], "E07000199": [30, 0.0], "E07000200": [75, 0.1], "E07000202": [126, 0.1], "E07000203": [86, 0.1], "E07000207": [90, 0.1], "E07000208": [43, 0.1], "E07000209": [96, 0.1], "E07000210": [69, 0.1], "E07000211": [90, 0.1], "E07000212": [46, 0.1], "E07000213": [39, 0.0], "E07000214": [39, 0.0], "E07000215": [61, 0.1], "E07000216": [105, 0.1], "E07000217": [54, 0.1], "E07000218": [34, 0.1], "E07000219": [48, 0.0], "E07000220": [36, 0.0], "E07000221": [93, 0.1], "E07000222": [94, 0.1], "E07000223": [90, 0.1], "E07000224": [151, 0.1], "E07000225": [160, 0.1], "E07000226": [64, 0.1], "E07000227": [127, 0.1], "E07000228": [141, 0.1], "E07000229": [144, 0.1], "E07000234": [57, 0.1], "E07000235": [104, 0.1], "E07000236": [32, 0.0], "E07000237": [83, 0.1], "E07000238": [58, 0.0], "E07000239": [47, 0.0], "E07000240": [87, 0.1], "E07000241": [74, 0.1], "E07000242": [90, 0.1], "E07000243": [47, 0.1], "E07000244": [219, 0.1], "E07000245": [187, 0.1], "E07000246": [143, 0.1], "E08000001": [91, 0.0], "E08000002": [96, 0.0], "E08000003": [351, 0.1], "E08000004": [79, 0.0], "E08000005": [62, 0.0], "E08000006": [144, 0.1], "E08000007": [162, 0.1], "E08000008": [94, 0.0], "E08000009": [128, 0.1], "E08000010": [134, 0.0], "E08000011": [48, 0.0], "E08000012": [292, 0.1], "E08000013": [71, 0.0], "E08000014": [135, 0.0], "E08000015": [214, 0.1], "E08000016": [76, 0.0], "E08000017": [97, 0.0], "E08000018": [91, 0.0], "E08000019": [406, 0.1], "E08000021": [167, 0.1], "E08000022": [153, 0.1], "E08000023": [59, 0.0], "E08000024": [99, 0.0], "E08000025": [414, 0.0], "E08000026": [99, 0.0], "E08000027": [103, 0.0], "E08000028": [64, 0.0], "E08000029": [90, 0.0], "E08000030": [65, 0.0], "E08000031": [73, 0.0], "E08000032": [183, 0.0], "E08000033": [203, 0.1], "E08000034": [207, 0.0], "E08000035": [460, 0.1], "E08000036": [131, 0.0], "E08000037": [86, 0.0], "E09000001": [12, 0.1], "E09000002": [45, 0.0], "E09000003": [222, 0.1], "E09000004": [90, 0.0], "E09000005": [153, 0.0], "E09000006": [192, 0.1], "E09000007": [298, 0.1], "E09000008": [170, 0.0], "E09000009": [189, 0.1], "E09000010": [112, 0.0], "E09000011": [180, 0.1], "E09000012": [313, 0.1], "E09000013": [199, 0.1], "E09000014": [307, 0.1], "E09000015": [54, 0.0], "E09000016": [100, 0.0], "E09000017": [87, 0.0], "E09000018": [122, 0.0], "E09000019": [282, 0.1], "E09000020": [207, 0.1], "E09000021": [133, 0.1], "E09000022": [329, 0.1], "E09000023": [308, 0.1], "E09000024": [128, 0.1], "E09000025": [92, 0.0], "E09000026": [75, 0.0], "E09000027": [267, 0.1], "E09000028": [326, 0.1], "E09000029": [117, 0.1], "E09000030": [281, 0.1], "E09000031": [198, 0.1], "E09000032": [269, 0.1], "E09000033": [292, 0.1], "W06000001": [46, 0.1], "W06000002": [147, 0.1], "W06000003": [105, 0.1], "W06000004": [72, 0.1], "W06000005": [84, 0.1], "W06000006": [75, 0.1], "W06000008": [135, 0.2], "W06000009": [174, 0.1], "W06000010": [161, 0.1], "W06000011": [171, 0.1], "W06000012": [67, 0.0], "W06000013": [76, 0.1], "W06000014": [113, 0.1], "W06000015": [267, 0.1], "W06000016": [119, 0.1], "W06000018": [67, 0.0], "W06000019": [34, 0.1], "W06000020": [46, 0.0], "W06000021": [96, 0.1], "W06000022": [111, 0.1], "W06000023": [188, 0.1], "W06000024": [26, 0.0]}, "2": {"E06000001": [40, 0.0], "E06000002": [59, 0.0], "E06000003": [97, 0.1], "E06000004": [128, 0.1], "E06000005": [71, 0.1], "E06000006": [72, 0.1], "E06000007": [170, 0.1], "E06000008": [81, 0.1], "E06000009": [130, 0.1], "E06000010": [214, 0.1], "E06000011": [255, 0.1], "E06000012": [125, 0.1], "E06000013": [109, 0.1], "E06000014": [200, 0.1], "E06000015": [136, 0.1], "E06000016": [149, 0.0], "E06000017": [26, 0.1], "E06000018": [249, 0.1], "E06000019": [182, 0.1], "E06000020": [105, 0.1], "E06000021": [130, 0.1], "E06000022": [255, 0.1], "E06000023": [721, 0.2], "E06000024": [206, 0.1], "E06000025": [231, 0.1], "E06000026": [235, 0.1], "E06000027": [159, 0.1], "E06000030": [146, 0.1], "E06000031": [116, 0.1], "E06000032": [75, 0.0], "E06000033": [197, 0.1], "E06000034": [70, 0.0], "E06000035": [175, 0.1], "E06000036": [67, 0.1], "E06000037": [86, 0.1], "E06000038": [134, 0.1], "E06000039": [57, 0.0], "E06000040": [123, 0.1], "E06000041": [95, 0.1], "E06000042": [186, 0.1], "E06000043": [684, 0.2], "E06000044": [186, 0.1], "E06000045": [246, 0.1], "E06000046": [168, 0.1], "E06000047": [369, 0.1], "E06000049": [337, 0.1], "E06000050": [252, 0.1], "E06000051": [259, 0.1], "E06000052": [732, 0.1], "E06000054": [473, 0.1], "E06000055": [108, 0.1], "E06000056": [184, 0.1], "E06000057": [267, 0.1], "E06000058": [447, 0.1], "E06000059": [458, 0.1], "E06000060": [390, 0.1], "E06000061": [248, 0.1], "E06000062": [323, 0.1], "E07000008": [245, 0.2], "E07000009": [77, 0.1], "E07000010": [74, 0.1], "E07000011": [157, 0.1], "E07000012": [127, 0.1], "E07000026": [75, 0.1], "E07000027": [47, 0.1], "E07000028": [83, 0.1], "E07000029": [53, 0.1], "E07000030": [64, 0.1], "E07000031": [198, 0.2], "E07000032": [100, 0.1], "E07000033": [38, 0.0], "E07000034": [79, 0.1], "E07000035": [89, 0.1], "E07000036": [67, 0.1], "E07000037": [100, 0.1], "E07000038": [61, 0.1], "E07000039": [69, 0.1], "E07000040": [184, 0.1], "E07000041": [194, 0.1], "E07000042": [108, 0.1], "E07000043": [90, 0.1], "E07000044": [206, 0.2], "E07000045": [197, 0.1], "E07000046": [85, 0.1], "E07000047": [108, 0.2], "E07000061": [135, 0.1], "E07000062": [164, 0.2], "E07000063": [178, 0.2], "E07000064": [112, 0.1], "E07000065": [158, 0.1], "E07000066": [93, 0.0], "E07000067": [111, 0.1], "E07000068": [49, 0.1], "E07000069": [42, 0.0], "E07000070": [143, 0.1], "E07000071": [166, 0.1], "E07000072": [81, 0.1], "E07000073": [59, 0.1], "E07000074": [62, 0.1], "E07000075": [49, 0.1], "E07000076": [123, 0.1], "E07000077": [70, 0.1], "E07000078": [118, 0.1], "E07000079": [87, 0.1], "E07000080": [69, 0.1], "E07000081": [83, 0.1], "E07000082": [186, 0.2], "E07000083": [73, 0.1], "E07000084": [146, 0.1], "E07000085": [101, 0.1], "E07000086": [104, 0.1], "E07000087": [89, 0.1], "E07000088": [50, 0.1], "E07000089": [62, 0.1], "E07000090": [96, 0.1], "E07000091": [134, 0.1], "E07000092": [68, 0.1], "E07000093": [84, 0.1], "E07000094": [123, 0.1], "E07000095": [47, 0.0], "E07000096": [140, 0.1], "E07000098": [45, 0.0], "E07000099": [121, 0.1], "E07000102": [34, 0.0], "E07000103": [57, 0.1], "E07000105": [90, 0.1], "E07000106": [173, 0.1], "E07000107": [55, 0.0], "E07000108": [116, 0.1], "E07000109": [45, 0.0], "E07000110": [143, 0.1], "E07000111": [106, 0.1], "E07000112": [107, 0.1], "E07000113": [132, 0.1], "E07000114": [157, 0.1], "E07000115": [97, 0.1], "E07000116": [106, 0.1], "E07000117": [49, 0.1], "E07000118": [114, 0.1], "E07000119": [72, 0.1], "E07000120": [57, 0.1], "E07000121": [174, 0.1], "E07000122": [62, 0.1], "E07000123": [112, 0.1], "E07000124": [38, 0.1], "E07000125": [55, 0.1], "E07000126": [57, 0.1], "E07000127": [82, 0.1], "E07000128": [74, 0.1], "E07000129": [57, 0.1], "E07000130": [119, 0.1], "E07000131": [86, 0.1], "E07000132": [64, 0.1], "E07000133": [33, 0.1], "E07000134": [66, 0.1], "E07000135": [27, 0.0], "E07000136": [44, 0.1], "E07000137": [88, 0.1], "E07000138": [114, 0.1], "E07000139": [54, 0.0], "E07000140": [57, 0.1], "E07000141": [84, 0.1], "E07000142": [60, 0.1], "E07000143": [132, 0.1], "E07000144": [110, 0.1], "E07000145": [69, 0.1], "E07000146": [107, 0.1], "E07000147": [127, 0.1], "E07000148": [259, 0.2], "E07000149": [138, 0.1], "E07000163": [43, 0.1], "E07000164": [58, 0.1], "E07000165": [142, 0.1], "E07000166": [31, 0.1], "E07000167": [32, 0.1], "E07000168": [114, 0.1], "E07000169": [47, 0.1], "E07000170": [64, 0.1], "E07000171": [84, 0.1], "E07000172": [83, 0.1], "E07000173": [80, 0.1], "E07000174": [83, 0.1], "E07000175": [96, 0.1], "E07000176": [123, 0.1], "E07000177": [141, 0.1], "E07000178": [189, 0.1], "E07000179": [120, 0.1], "E07000180": [135, 0.1], "E07000181": [99, 0.1], "E07000187": [223, 0.2], "E07000188": [115, 0.1], "E07000189": [151, 0.1], "E07000192": [50, 0.0], "E07000193": [97, 0.1], "E07000194": [68, 0.1], "E07000195": [72, 0.1], "E07000196": [110, 0.1], "E07000197": [116, 0.1], "E07000198": [60, 0.1], "E07000199": [38, 0.0], "E07000200": [68, 0.1], "E07000202": [113, 0.1], "E07000203": [91, 0.1], "E07000207": [111, 0.1], "E07000208": [54, 0.1], "E07000209": [107, 0.1], "E07000210": [71, 0.1], "E07000211": [119, 0.1], "E07000212": [55, 0.1], "E07000213": [50, 0.0], "E07000214": [60, 0.1], "E07000215": [62, 0.1], "E07000216": [129, 0.1], "E07000217": [55, 0.1], "E07000218": [57, 0.1], "E07000219": [85, 0.1], "E07000220": [82, 0.1], "E07000221": [91, 0.1], "E07000222": [127, 0.1], "E07000223": [72, 0.1], "E07000224": [144, 0.1], "E07000225": [169, 0.1], "E07000226": [79, 0.1], "E07000227": [141, 0.1], "E07000228": [121, 0.1], "E07000229": [149, 0.1], "E07000234": [61, 0.1], "E07000235": [99, 0.1], "E07000236": [51, 0.1], "E07000237": [82, 0.1], "E07000238": [112, 0.1], "E07000239": [60, 0.1], "E07000240": [103, 0.1], "E07000241": [77, 0.1], "E07000242": [97, 0.1], "E07000243": [59, 0.1], "E07000244": [254, 0.1], "E07000245": [165, 0.1], "E07000246": [159, 0.1], "E08000001": [138, 0.0], "E08000002": [109, 0.1], "E08000003": [497, 0.1], "E08000004": [109, 0.0], "E08000005": [107, 0.0], "E08000006": [200, 0.1], "E08000007": [203, 0.1], "E08000008": [128, 0.1], "E08000009": [143, 0.1], "E08000010": [180, 0.1], "E08000011": [71, 0.0], "E08000012": [368, 0.1], "E08000013": [110, 0.1], "E08000014": [188, 0.1], "E08000015": [287, 0.1], "E08000016": [128, 0.1], "E08000017": [244, 0.1], "E08000018": [131, 0.0], "E08000019": [497, 0.1], "E08000021": [285, 0.1], "E08000022": [148, 0.1], "E08000023": [78, 0.1], "E08000024": [129, 0.0], "E08000025": [588, 0.1], "E08000026": [167, 0.0], "E08000027": [142, 0.0], "E08000028": [114, 0.0], "E08000029": [107, 0.0], "E08000030": [94, 0.0], "E08000031": [96, 0.0], "E08000032": [275, 0.1], "E08000033": [214, 0.1], "E08000034": [252, 0.1], "E08000035": [558, 0.1], "E08000036": [206, 0.1], "E08000037": [123, 0.1], "E09000001": [13, 0.2], "E09000002": [56, 0.0], "E09000003": [222, 0.1], "E09000004": [116, 0.0], "E09000005": [169, 0.0], "E09000006": [269, 0.1], "E09000007": [301, 0.1], "E09000008": [267, 0.1], "E09000009": [193, 0.1], "E09000010": [124, 0.0], "E09000011": [200, 0.1], "E09000012": [328, 0.1], "E09000013": [179, 0.1], "E09000014": [275, 0.1], "E09000015": [65, 0.0], "E09000016": [106, 0.0], "E09000017": [105, 0.0], "E09000018": [157, 0.1], "E09000019": [291, 0.1], "E09000020": [173, 0.1], "E09000021": [161, 0.1], "E09000022": [416, 0.1], "E09000023": [332, 0.1], "E09000024": [148, 0.1], "E09000025": [124, 0.0], "E09000026": [91, 0.0], "E09000027": [232, 0.1], "E09000028": [336, 0.1], "E09000029": [135, 0.1], "E09000030": [406, 0.1], "E09000031": [208, 0.1], "E09000032": [327, 0.1], "E09000033": [228, 0.1], "W06000001": [54, 0.1], "W06000002": [123, 0.1], "W06000003": [123, 0.1], "W06000004": [97, 0.1], "W06000005": [111, 0.1], "W06000006": [116, 0.1], "W06000008": [109, 0.2], "W06000009": [127, 0.1], "W06000010": [187, 0.1], "W06000011": [261, 0.1], "W06000012": [130, 0.1], "W06000013": [135, 0.1], "W06000014": [106, 0.1], "W06000015": [311, 0.1], "W06000016": [145, 0.1], "W06000018": [110, 0.1], "W06000019": [49, 0.1], "W06000020": [51, 0.1], "W06000021": [119, 0.1], "W06000022": [113, 0.1], "W06000023": [168, 0.1], "W06000024": [32, 0.1]}}}